sample_data_generator/__init__.py
sample_data_generator/main.py
sample_data_generator/schema.py
sample_data_generator/core/__init__.py
sample_data_generator/core/connections.py
sample_data_generator/core/sample_data_generator.py
sample_data_generator/dao/__init__.py
sample_data_generator/dao/base.py
sample_data_generator/dao/redis/__init__.py
sample_data_generator/dao/redis/base.py
sample_data_generator/dao/redis/capacity_report.py
sample_data_generator/dao/redis/feed.py
sample_data_generator/dao/redis/key_schema.py
sample_data_generator/dao/redis/meter_reading.py
sample_data_generator/dao/redis/metric.py
sample_data_generator/dao/redis/site.py
sample_data_generator/dao/redis/site_geo.py
sample_data_generator/dao/redis/site_stats.py
sample_data_generator/fixtures/sites.json
sample_data_generator/models/__init__.py
sample_data_generator/models/models.py
sample_data_generator/models/rate_limiter.py
sample_data_generator/scripts/__init__.py
sample_data_generator/scripts/compare_and_update.lua
sample_data_generator/scripts/compare_and_update.py
tests/models/__init__.py
tests/models/test_models.py
redisolar_sample_data_generator-1.0.5.dist-info/LICENSE.txt
redisolar_sample_data_generator-1.0.5.dist-info/METADATA
redisolar_sample_data_generator-1.0.5.dist-info/WHEEL
redisolar_sample_data_generator-1.0.5.dist-info/entry_points.txt
redisolar_sample_data_generator-1.0.5.dist-info/top_level.txt
redisolar_sample_data_generator-1.0.5.dist-info/RECORD
