Metadata-Version: 2.1
Name: redisolar-sample-data-generator
Version: 1.0.5
Summary: A sample data generator for Redis University's example application.
Home-page: https://github.com/redislabs-training/redisolar-sample-data-generator/
Author: Andrew Brookins
Author-email: andrew.brookins@redislabs.com
License: UNKNOWN
Platform: UNKNOWN
Classifier: Programming Language :: Python :: 3
Classifier: License :: OSI Approved :: BSD License
Classifier: Operating System :: OS Independent
Requires-Python: >=3.7
Requires-Dist: redis (==3.5.0)
Requires-Dist: progress (==1.5)
Requires-Dist: mypy (==0.761)
Requires-Dist: hiredis (==1.0.1)
Requires-Dist: click (==7.1.1)
Requires-Dist: marshmallow-dataclass[enum,union] (==7.3.0)
Provides-Extra: dev
Requires-Dist: reorder-python-imports (==1.9.0) ; extra == 'dev'
Requires-Dist: yapf (==0.29.0) ; extra == 'dev'
Requires-Dist: pylint (==2.4.4) ; extra == 'dev'
Requires-Dist: pytest (==5.4.1) ; extra == 'dev'
Requires-Dist: twine (==3.1.1) ; extra == 'dev'
